hecatomb/__init__.py
hecatomb/__main__.py
hecatomb/hecatomb.CITATION
hecatomb/hecatomb.LICENSE
hecatomb/hecatomb.VERSION
hecatomb/snakemake/config/config.yaml
hecatomb/snakemake/config/dbFiles.yaml
hecatomb/snakemake/config/immutable.yaml
hecatomb/snakemake/profile/default/config.yaml
hecatomb/snakemake/profile/example_slurm/config.yaml
hecatomb/snakemake/profile/example_slurm/slurm-status.py
hecatomb/snakemake/workflow/AddHost.smk
hecatomb/snakemake/workflow/DownloadDB.smk
hecatomb/snakemake/workflow/Hecatomb.smk
hecatomb/snakemake/workflow/combineOutputs.smk
hecatomb/snakemake/workflow/container/bbmap
hecatomb/snakemake/workflow/container/bedtools
hecatomb/snakemake/workflow/container/canu
hecatomb/snakemake/workflow/container/curl
hecatomb/snakemake/workflow/container/koverage
hecatomb/snakemake/workflow/container/krona
hecatomb/snakemake/workflow/container/megahit
hecatomb/snakemake/workflow/container/metaflye
hecatomb/snakemake/workflow/container/minimap2
hecatomb/snakemake/workflow/container/mmseqs2
hecatomb/snakemake/workflow/container/pigz
hecatomb/snakemake/workflow/container/pysam
hecatomb/snakemake/workflow/container/samtools
hecatomb/snakemake/workflow/container/seqkit
hecatomb/snakemake/workflow/container/trimnami
hecatomb/snakemake/workflow/envs/bbmap.yaml
hecatomb/snakemake/workflow/envs/bedtools.yaml
hecatomb/snakemake/workflow/envs/canu.yaml
hecatomb/snakemake/workflow/envs/curl.yaml
hecatomb/snakemake/workflow/envs/koverage.yaml
hecatomb/snakemake/workflow/envs/krona.yaml
hecatomb/snakemake/workflow/envs/megahit.yaml
hecatomb/snakemake/workflow/envs/metaflye.yaml
hecatomb/snakemake/workflow/envs/minimap2.yaml
hecatomb/snakemake/workflow/envs/mmseqs2.yaml
hecatomb/snakemake/workflow/envs/pigz.yaml
hecatomb/snakemake/workflow/envs/pysam.yaml
hecatomb/snakemake/workflow/envs/samtools.yaml
hecatomb/snakemake/workflow/envs/seqkit.yaml
hecatomb/snakemake/workflow/envs/trimnami.yaml
hecatomb/snakemake/workflow/report/host_removed_counts.rst
hecatomb-1.3.4.dist-info/licenses/LICENSE
hecatomb-1.3.4.dist-info/METADATA
hecatomb-1.3.4.dist-info/WHEEL
hecatomb-1.3.4.dist-info/entry_points.txt
hecatomb-1.3.4.dist-info/top_level.txt
hecatomb-1.3.4.dist-info/RECORD
