Metadata-Version: 2.4
Name: hecatomb
Version: 1.3.4
Summary: Viral metagenomics framework for short and longreads
Home-page: https://github.com/shandley/hecatomb
Author: Michael Roach
Author-email: beardymcjohnface@gmail.com
Requires-Python: >=3.9
License-File: LICENSE
Requires-Dist: snakemake>=8
Requires-Dist: pulp<2.8
Requires-Dist: pyyaml>=6.0
Requires-Dist: Click>=8.1.3
Requires-Dist: metasnek>=0.0.7
Requires-Dist: snaketool-utils>=0.0.5
Dynamic: author
Dynamic: author-email
Dynamic: description
Dynamic: description-content-type
Dynamic: home-page
Dynamic: license-file
Dynamic: requires-dist
Dynamic: requires-python
Dynamic: summary
